odoo/addons/website_sale_wishlist_hide_price/README.rst
odoo/addons/website_sale_wishlist_hide_price/__init__.py
odoo/addons/website_sale_wishlist_hide_price/__manifest__.py
odoo/addons/website_sale_wishlist_hide_price/i18n/it.po
odoo/addons/website_sale_wishlist_hide_price/i18n/website_sale_wishlist_hide_price.pot
odoo/addons/website_sale_wishlist_hide_price/readme/CONTRIBUTORS.md
odoo/addons/website_sale_wishlist_hide_price/readme/DESCRIPTION.md
odoo/addons/website_sale_wishlist_hide_price/static/description/icon.png
odoo/addons/website_sale_wishlist_hide_price/static/description/index.html
odoo/addons/website_sale_wishlist_hide_price/static/tests/tours/website_sale_wishlist_hide_price_tour.esm.js
odoo/addons/website_sale_wishlist_hide_price/tests/__init__.py
odoo/addons/website_sale_wishlist_hide_price/tests/test_tour.py
odoo/addons/website_sale_wishlist_hide_price/views/website_sale_template.xml
odoo_addon_website_sale_wishlist_hide_price-18.0.1.0.0.3.dist-info/METADATA
odoo_addon_website_sale_wishlist_hide_price-18.0.1.0.0.3.dist-info/WHEEL
odoo_addon_website_sale_wishlist_hide_price-18.0.1.0.0.3.dist-info/top_level.txt
odoo_addon_website_sale_wishlist_hide_price-18.0.1.0.0.3.dist-info/RECORD
